[
 {
  "docstatus": 0,
  "doctype": "Workflow Action Master",
  "modified": "2025-09-01 09:14:11.731325",
  "name": "Extend",
  "workflow_action_name": "Extend"
 },
 {
  "docstatus": 0,
  "doctype": "Workflow Action Master",
  "modified": "2023-09-14 18:42:31.760319",
  "name": "Check in",
  "workflow_action_name": "Check in"
 },
 {
  "docstatus": 0,
  "doctype": "Workflow Action Master",
  "modified": "2023-09-14 18:42:44.549130",
  "name": "Check out",
  "workflow_action_name": "Check out"
 },
 {
  "docstatus": 0,
  "doctype": "Workflow Action Master",
  "modified": "2022-07-05 18:30:39.351277",
  "name": "Cancel",
  "workflow_action_name": "Cancel"
 },
 {
  "docstatus": 0,
  "doctype": "Workflow Action Master",
  "modified": "2023-07-09 17:56:38.613402",
  "name": "Request",
  "workflow_action_name": "Request"
 }
]